reflex_okta_auth/__init__.py
reflex_okta_auth/config.py
reflex_okta_auth/endpoints.py
reflex_okta_auth/funcs.py
reflex_okta_auth/messageListener.js
reflex_okta_auth/message_listener.py
reflex_okta_auth/oidc.py
reflex_okta_auth/state.py
reflex_okta_auth/types.py
reflex_okta_auth/ui.py
reflex_okta_auth-0.2.0.dist-info/METADATA
reflex_okta_auth-0.2.0.dist-info/WHEEL
reflex_okta_auth-0.2.0.dist-info/RECORD
