Metadata-Version: 2.4
Name: reflex-okta-auth
Version: 0.2.0
Summary: Integration with Okta server-side SSO
Project-URL: homepage, https://reflex.dev/
Project-URL: documentation, https://enterprise.reflex.dev
Author-email: Masen Furer <masen@reflex.dev>
License-Expression: LicenseRef-Proprietary
Keywords: python,reflex,reflex-enterprise
Requires-Python: <4.0,>=3.10
Requires-Dist: cryptography
Requires-Dist: okta-jwt-verifier
Requires-Dist: reflex-enterprise>=0.3.0
